{"cameraMode":{"drawMode":0,"name":"Shaded","section":"Shading Mode"},"sceneLighting":true,"audioPlay":false,"sceneViewState":{"m_AlwaysRefresh":false,"showFog":true,"showSkybox":true,"showFlares":true,"showImageEffects":true,"showParticleSystems":true,"showVisualEffectGraphs":true,"m_FxEnabled":true},"in2DMode":false,"pivot":{"x":0.0,"y":524.8892822265625,"z":0.0},"rotation":{"x":0.08750807493925095,"y":0.33224382996559145,"z":-0.03121957555413246,"w":0.938994288444519},"size":321.1845703125,"orthographic":false}